tiny3d-0.0.0.dist-info/RECORD
tiny3d-0.0.0.dist-info/WHEEL
tiny3d-0.0.0.dist-info/entry_points.txt
tiny3d-0.0.0.dist-info/top_level.txt
tiny3d-0.0.0.dist-info/LICENSE.txt
tiny3d-0.0.0.dist-info/METADATA
tiny3d/_build_config.py
tiny3d/__init__.py
tiny3d/cpu/pybind.cpython-39-darwin.so
tiny3d/cpu/__init__.py
